PyBookmark-1.1.1.1.data/data/data/addr.json
PyBookmark-1.1.1.1.data/data/data/bookmarks.html
PyBookmark-1.1.1.1.data/data/data/bookmarks_test.html
pybookmark/VERSION
pybookmark/__init__.py
pybookmark/bookmarks_class.py
pybookmark/bookmarks_parse.py
pybookmark/icon.png
pybookmark/pybookmarkjsonviewer.py
pybookmark/support.py
scripts/PyBookmark_viewer.py
scripts/bookmarks_merge.py
PyBookmark-1.1.1.1.dist-info/LICENSE
PyBookmark-1.1.1.1.dist-info/METADATA
PyBookmark-1.1.1.1.dist-info/WHEEL
PyBookmark-1.1.1.1.dist-info/entry_points.txt
PyBookmark-1.1.1.1.dist-info/top_level.txt
PyBookmark-1.1.1.1.dist-info/RECORD
