Metadata-Version: 2.1
Name: PyBookmark
Version: 1.1.1.1
Summary: A Bookmark.html file parser, merger and data viewer using pure python
Home-page: https://github.com/Crumbs350/pybookmark
Author: Crumbs
Author-email: 22521102+Crumbs350@users.noreply.github.com
Maintainer: Crumbs
Maintainer-email: 22521102+Crumbs350@users.noreply.github.com
License: LICENSE
Keywords: python bookmark json tkinter privacy
Classifier: Programming Language :: Python :: 3
Classifier: License :: OSI Approved :: MIT License
Classifier: Intended Audience :: End Users/Desktop
Classifier: Topic :: Text Processing :: Markup :: HTML
License-File: LICENSE
Requires-Dist: pyyaml
